TechfinDataPipeline/__init__.py
TechfinDataPipeline/data_tools.py
TechfinDataPipeline/invoice_struct.py
TechfinDataPipeline/nfe_xml_parser.py
TechfinDataPipeline-0.0.26.dist-info/METADATA
TechfinDataPipeline-0.0.26.dist-info/WHEEL
TechfinDataPipeline-0.0.26.dist-info/top_level.txt
TechfinDataPipeline-0.0.26.dist-info/RECORD
