Metadata-Version: 2.1
Name: TechfinDataPipeline
Version: 0.0.26
Summary: UNKNOWN
Home-page: https://totvstfs.visualstudio.com/Techfin/_git/techfin-ds-golden-data-pipeline
Author: TOTVS Techfin
Author-email: guilherme.spadaccia@totvs.com.br
License: MIT
Keywords: TOTVS,Techfin,Golden Data Parser
Platform: UNKNOWN
Classifier: Development Status :: 3 - Alpha
Classifier: Intended Audience :: Developers
Classifier: Topic :: Software Development :: Build Tools
Classifier: License :: OSI Approved :: MIT License
Classifier: Programming Language :: Python :: 3.4
Classifier: Programming Language :: Python :: 3.5
Classifier: Programming Language :: Python :: 3.6
Classifier: Programming Language :: Python :: 3.7
Requires-Dist: pycarol[dataframe]
